anyblok_address/__init__.py
anyblok_address/bloks/__init__.py
anyblok_address/bloks/address/__init__.py
anyblok_address/bloks/address/address.py
anyblok_address/bloks/address/tests/__init__.py
anyblok_address/bloks/address/tests/test_model.py
anyblok_address-1.2.2.dist-info/LICENSE
anyblok_address-1.2.2.dist-info/METADATA
anyblok_address-1.2.2.dist-info/WHEEL
anyblok_address-1.2.2.dist-info/entry_points.txt
anyblok_address-1.2.2.dist-info/top_level.txt
anyblok_address-1.2.2.dist-info/RECORD
