Metadata-Version: 1.1
Name: anyblok-address
Version: 1.2.2
Summary: Address management
Home-page: http://docs.anyblok-address.anyblok.org/1.2.2
Author: Franck Bret, Hugo Quezada
Author-email: f.bret@sensee.com, h.quezada@sensee.com
License: UNKNOWN
Keywords: anyblok_address
Platform: UNKNOWN
Classifier: Development Status :: 2 - Pre-Alpha
Classifier: Intended Audience :: Developers
Classifier: Natural Language :: English
Classifier: Programming Language :: Python :: 3
Classifier: Programming Language :: Python :: 3.3
Classifier: Programming Language :: Python :: 3.4
Classifier: Programming Language :: Python :: 3.5
Classifier: Programming Language :: Python :: 3.6
